fsmedhro_diva/__init__.py
fsmedhro_diva/admin.py
fsmedhro_diva/apps.py
fsmedhro_diva/models.py
fsmedhro_diva/tests.py
fsmedhro_diva/urls.py
fsmedhro_diva/views.py
fsmedhro_diva/migrations/0001_initial.py
fsmedhro_diva/migrations/0002_empfaenger_required.py
fsmedhro_diva/migrations/0003_alter_empfaenger_required.py
fsmedhro_diva/migrations/__init__.py
fsmedhro_diva/templates/fsmedhro_diva/send.html
django_fsmedhro_diva-0.0.3.dist-info/LICENSE
django_fsmedhro_diva-0.0.3.dist-info/METADATA
django_fsmedhro_diva-0.0.3.dist-info/WHEEL
django_fsmedhro_diva-0.0.3.dist-info/top_level.txt
django_fsmedhro_diva-0.0.3.dist-info/RECORD
