Metadata-Version: 2.1
Name: django-fsmedhro-diva
Version: 0.0.3
Summary: Django-App für die Auswertung von Veranstaltungen
Home-page: https://github.com/hutchison/django-exoral
Author: Martin Darmüntzel
Author-email: martin@trivialanalog.de
License: MIT License
Platform: UNKNOWN
Classifier: Environment :: Web Environment
Classifier: Framework :: Django
Classifier: Framework :: Django :: 3.0
Classifier: Intended Audience :: Developers
Classifier: License :: OSI Approved :: MIT License
Classifier: Operating System :: OS Independent
Classifier: Programming Language :: Python
Classifier: Programming Language :: Python :: 3.6
Classifier: Programming Language :: Python :: 3.7
Classifier: Programming Language :: Python :: 3.8
Classifier: Programming Language :: Python :: 3.9
Classifier: Programming Language :: Python :: 3.10
Classifier: Topic :: Internet :: WWW/HTTP
Classifier: Topic :: Internet :: WWW/HTTP :: Dynamic Content
Requires-Python: >=3.5
License-File: LICENSE
Requires-Dist: Django (>=3.0)
Requires-Dist: django-fsmedhro-core (>=0.2.6)
